w3socket/__init__.py
w3socket/config.py
w3socket/policyserver.py
w3socket/server.py
w3socket-0.1.1.dist-info/LICENSE
w3socket-0.1.1.dist-info/METADATA
w3socket-0.1.1.dist-info/WHEEL
w3socket-0.1.1.dist-info/top_level.txt
w3socket-0.1.1.dist-info/RECORD
