Metadata-Version: 2.1
Name: w3socket
Version: 0.1.1
Summary: socket implementation for w3
Home-page: http://pypi.python.org/pypi/w3socket
License: UNKNOWN
Platform: UNKNOWN
Classifier: License :: OSI Approved :: MIT License
Classifier: Programming Language :: Python
Classifier: Operating System :: MacOS :: MacOS X
Classifier: Operating System :: POSIX
Classifier: Operating System :: Microsoft :: Windows
Classifier: Topic :: Internet
Classifier: Topic :: Software Development :: Libraries :: Python Modules
Classifier: Intended Audience :: Developers
Classifier: Development Status :: 4 - Beta
License-File: LICENSE
Requires-Dist: gevent
Requires-Dist: greenlet
Requires-Dist: pillow
Requires-Dist: psutil
Requires-Dist: pyinstaller
Requires-Dist: pynput
Requires-Dist: pyscreenshot
Requires-Dist: tabulate
Requires-Dist: web3node
